ezprinting/__init__.py
ezprinting/print_job.py
ezprinting/print_server.py
ezprinting/printer.py
ezprinting-0.3.0.dist-info/LICENSE.txt
ezprinting-0.3.0.dist-info/WHEEL
ezprinting-0.3.0.dist-info/METADATA
ezprinting-0.3.0.dist-info/RECORD
