Metadata-Version: 2.1
Name: ezprinting
Version: 0.3.0
Summary: Python package to easily print to a printer configured on either a CUPS server or Google Cloud Print.
Home-page: https://github.com/mbello/ezprinting
License: MIT
Keywords: google cloud print,cloud print,cups,printing
Author: Marcelo Bello
Requires-Python: >=3.6
Classifier: License :: OSI Approved :: MIT License
Classifier: Programming Language :: Python :: 3
Classifier: Programming Language :: Python :: 3.6
Classifier: Programming Language :: Python :: 3.7
Classifier: Programming Language :: Python :: 3.8
Requires-Dist: pycups (>=1.9.74)
Project-URL: Repository, https://github.com/mbello/ezprinting
